{
  "project_info": {
    "project_number": "456903705487",
    "project_id": "gettravel-de8b1",
    "storage_bucket": "gettravel-de8b1.appspot.com"
  },
  "client": [
    {
      "client_info": {
        "mobilesdk_app_id": "1:456903705487:android:5ab4d809c7e645d357c1fa",
        "android_client_info": {
          "package_name": "com.example.yoohtravel"
        }
      },
      "oauth_client": [
        {
          "client_id": "456903705487-96t2c5og1alnh29g2j962o6iuu1v3s1a.apps.googleusercontent.com",
          "client_type": 1,
          "android_info": {
            "package_name": "com.example.yoohtravel",
            "certificate_hash": "5260295ce01da159892c7cfbbb5c335969f8987f"
          }
        },
        {
          "client_id": "456903705487-0f6dopikvue91ji1sbmtgafn9fsj9jku.apps.googleusercontent.com",
          "client_type": 3
        }
      ],
      "api_key": [
        {
          "current_key": "AIzaSyAG3GxKdXC6k3BC74hmRdUqiBYHKxCgu_c"
        }
      ],
      "services": {
        "appinvite_service": {
          "other_platform_oauth_client": [
            {
              "client_id": "456903705487-0f6dopikvue91ji1sbmtgafn9fsj9jku.apps.googleusercontent.com",
              "client_type": 3
            }
          ]
        }
      }
    }
  ],
  "configuration_version": "1"
}